unrestricted_advex/__init__.py
unrestricted_advex/attacks.py
unrestricted_advex/eval_kit.py
unrestricted_advex/load_models.py
unrestricted_advex/plotting.py
unrestricted_advex-0.0.3.dist-info/METADATA
unrestricted_advex-0.0.3.dist-info/RECORD
unrestricted_advex-0.0.3.dist-info/WHEEL
unrestricted_advex-0.0.3.dist-info/top_level.txt
