Metadata-Version: 2.1
Name: unrestricted-advex
Version: 0.0.3
Summary: Evaluation code and mnist_baselines for the warmup to the unrestricted adversarial examples contest
Home-page: https://github.com/google/unrestricted-advex
Author: Tom Brown
Author-email: tombrown@google.com
License: UNKNOWN
Platform: UNKNOWN
Requires-Dist: tqdm (~=4.0)
Requires-Dist: cleverhans (~=2.1)
Requires-Dist: foolbox (~=1.3)
Requires-Dist: randomgen
